multiselectfield/__init__.py
multiselectfield/apps.py
multiselectfield/utils.py
multiselectfield/validators.py
multiselectfield/db/__init__.py
multiselectfield/db/fields.py
multiselectfield/forms/__init__.py
multiselectfield/forms/fields.py
multiselectfield/locale/es/LC_MESSAGES/django.mo
multiselectfield/locale/es/LC_MESSAGES/django.po
django_multiselectfield2-0.0.1.dist-info/COPYING.LGPLv3
django_multiselectfield2-0.0.1.dist-info/METADATA
django_multiselectfield2-0.0.1.dist-info/WHEEL
django_multiselectfield2-0.0.1.dist-info/top_level.txt
django_multiselectfield2-0.0.1.dist-info/RECORD
