Metadata-Version: 2.1
Name: django-multiselectfield2
Version: 0.0.1
Summary: Django multiple select field
Home-page: https://github.com/goinnn/django-multiselectfield
Author: Pablo Martin
Author-email: goinnn@gmail.com
License: LGPL 3
Keywords: django,multiple,select,field,choices
Classifier: Development Status :: 4 - Beta
Classifier: Framework :: Django
Classifier: License :: OSI Approved :: GNU Library or Lesser General Public License (LGPL)
Classifier: Programming Language :: Python :: 2
Classifier: Programming Language :: Python :: 2.6
Classifier: Programming Language :: Python :: 2.7
Classifier: Programming Language :: Python :: 3
Classifier: Programming Language :: Python :: 3.3
Classifier: Programming Language :: Python :: 3.4
Classifier: Programming Language :: Python :: 3.5
Classifier: Programming Language :: Python :: 3.6
Classifier: Programming Language :: Python :: 3.7
Classifier: Programming Language :: Python :: 3.8
License-File: COPYING.LGPLv3
